vepi/__init__.py
vepi/vena_etl.py
vepi/version.py
vepi-0.1.4.dist-info/licenses/LICENSE
vepi-0.1.4.dist-info/METADATA
vepi-0.1.4.dist-info/WHEEL
vepi-0.1.4.dist-info/top_level.txt
vepi-0.1.4.dist-info/RECORD
