Metadata-Version: 2.4
Name: vepi
Version: 0.1.4
Summary: A Python library for interacting with Vena's ETL API
Home-page: https://github.com/venasolutions/vena-etl-python-interface
Author: Greg Hetherington
Author-email: ghetherington@venacorp.com
Classifier: Programming Language :: Python :: 3
Classifier: License :: OSI Approved :: MIT License
Classifier: Operating System :: OS Independent
Requires-Python: >=3.7
License-File: LICENSE
Requires-Dist: requests>=2.25.1
Requires-Dist: pandas>=1.1.0
Dynamic: author
Dynamic: author-email
Dynamic: classifier
Dynamic: description
Dynamic: description-content-type
Dynamic: home-page
Dynamic: license-file
Dynamic: requires-dist
Dynamic: requires-python
Dynamic: summary
